mopidy_dleyna/__init__.py
mopidy_dleyna/backend.py
mopidy_dleyna/client.py
mopidy_dleyna/ext.conf
mopidy_dleyna/library.py
mopidy_dleyna/playback.py
mopidy_dleyna/translator.py
mopidy_dleyna/util.py
Mopidy_dLeyna-2.0.2.dist-info/LICENSE
Mopidy_dLeyna-2.0.2.dist-info/METADATA
Mopidy_dLeyna-2.0.2.dist-info/WHEEL
Mopidy_dLeyna-2.0.2.dist-info/entry_points.txt
Mopidy_dLeyna-2.0.2.dist-info/top_level.txt
Mopidy_dLeyna-2.0.2.dist-info/RECORD
